[
  {
    "video": "Hans Rosling: The River of Myths",
    "link": "https://www.youtube.com/watch?v=lYpX4l2UeZg",
    "category": "Gestures, Location, Textual , Visual",
    "textual": "Label and Annotation",
    "visual": "Graph, Static Visuals",
    "location": "Front 2D",
    "gesture": "Animation Trigger, Highlight, Move, Specify Position",
    "screenshots": "https://drive.google.com/drive/folders/1ePq5t9dCSr5hmjxxNrkdP2BTqCxX6cNx?usp=sharing"
  },
  {
    "video": "ACCELLION - Kitepoint",
    "link": "https://vimeo.com/109554081",
    "category": "Gestures, Location, Textual , Visual",
    "textual": "Title and Keyword",
    "visual": "Drawing, Icons, Static Visuals",
    "location": "Back 2D (Occlusion), Body, Front 2D",
    "gesture": "Animation Trigger, Follow-through",
    "screenshots": "https://drive.google.com/drive/folders/134FrEd8BqE5ninT3OfrSNqzCAlsbLG1w?usp=sharing"
  },
  {
    "video": "Ad ING-Coach Kate",
    "link": "https://vimeo.com/170481636",
    "category": "Location, Textual , Visual",
    "textual": "Title and Keyword",
    "visual": "Drawing, Graph, Static Visuals",
    "location": "Front 2D",
    "gesture": "",
    "screenshots": "https://drive.google.com/drive/folders/1jE67S_5vGbi60wYoNnyve-bDQlknMlfA?usp=sharing"
  },
  {
    "video": "2016_08 SKT 대구 Smart City",
    "link": "https://vimeo.com/185608623",
    "category": "Location, Textual , Visual",
    "textual": "Label and Annotation, Title and Keyword",
    "visual": "Icons, Screens, Static Visuals",
    "location": "3D Surface",
    "gesture": "",
    "screenshots": "https://drive.google.com/drive/folders/1sLLX-r5TELyRmt_NaRqE3YCZoK6cBGjb?usp=sharing"
  },
  {
    "video": "3 Mobile - Digital You",
    "link": "https://vimeo.com/71422033",
    "category": "Gestures, Location, Textual , Visual",
    "textual": "Label and Annotation, Profile, Title and Keyword",
    "visual": "Icons, Static Visuals",
    "location": "3D Surface, Body",
    "gesture": "Follow-through",
    "screenshots": "https://drive.google.com/drive/folders/1ozUGH6MQIZeVXCeRMyD2agU_0dqMXDBp?usp=sharing"
  },
  {
    "video": "3D infographic video of Rio de Janeiro city",
    "link": "https://www.youtube.com/watch?v=G0VO2qdsSB8",
    "category": "Location, Textual , Visual",
    "textual": "Label and Annotation, Title and Keyword",
    "visual": "Icons, Static Visuals",
    "location": "3D Surface",
    "gesture": "",
    "screenshots": "https://drive.google.com/drive/folders/1jcNrtnaEHpSzRv0Ds2L9WmParobWtrEp?usp=sharing"
  },
  {
    "video": "5 Text Graphics Trends for 2018",
    "link": "https://www.youtube.com/watch?v=XAVhyvdU5JM",
    "category": "Gestures, Location, Textual , Visual",
    "textual": "Label and Annotation, Profile, Speech Bubble, Title and Keyword",
    "visual": "Graph, Screens, Static Visuals",
    "location": "3D Surface, Back 2D (Occlusion), Body, Front 2D, Physical Object",
    "gesture": "Highlight, Move",
    "screenshots": "https://drive.google.com/drive/folders/1tx-mTCY9_p1SZn9v4ydlQ0YTB5jW__RX?usp=sharing"
  },
  {
    "video": "6ter - DEPART IMMEDIAT - Alt Version",
    "link": "https://vimeo.com/189427854",
    "category": "Gestures, Location, Textual , Visual",
    "textual": "Label and Annotation, Profile",
    "visual": "Graph, Icons, Static Visuals",
    "location": "3D Surface, Back 2D (Occlusion), Body, Front 2D, Physical Object",
    "gesture": "Animation Trigger, Highlight, Specify Position",
    "screenshots": "https://drive.google.com/drive/folders/1IAkZkZYe3mX4zh5K4ZOOeRHjAEon94lV?usp=sharing"
  },
  {
    "video": "A Tornado Hits The Weather Channel IMR",
    "link": "https://www.youtube.com/watch?v=0cODBQqaGTw",
    "category": "Gestures, Location, Textual , Visual",
    "textual": "Label and Annotation, List, Title and Keyword",
    "visual": "Icons, Static Visuals",
    "location": "3D Surface, Physical Object",
    "gesture": "Animation Trigger",
    "screenshots": "https://drive.google.com/drive/folders/1CZxcbZfk8KTQsgFWggCrHJt9CP2mCCDc?usp=sharing"
  },
  {
    "video": "Adidas - Low Waste Brand Film",
    "link": "https://vimeo.com/199539760",
    "category": "Gestures, Location, Textual , Visual",
    "textual": "Label and Annotation, Title and Keyword",
    "visual": "Drawing, Graph, Static Visuals",
    "location": "3D Surface, Back 2D (Occlusion), Front 2D, Physical Object",
    "gesture": "Animation Trigger, Follow-through, Highlight, Move",
    "screenshots": "https://drive.google.com/drive/folders/1M1oxgC9t-srGbSNlhfKm6BRpsiqvu2h7?usp=sharing"
  },
  {
    "video": "adidas by Stella McCartney Barricade SS15 - Compilation",
    "link": "https://vimeo.com/116164120",
    "category": "Gestures, Location, Textual , Visual",
    "textual": "Title and Keyword",
    "visual": "Icons, Static Visuals",
    "location": "3D Surface, Back 2D (Occlusion)",
    "gesture": "Animation Trigger, Move",
    "screenshots": "https://drive.google.com/drive/folders/1wc6s9T7IzhYQAXCpI_CSOUQ9_oNnYUdO?usp=sharing"
  },
  {
    "video": "Adidas Originals Unite All Originals feat. Run DMC and A-Trak All animations triggered",
    "link": "https://vimeo.com/73846042",
    "category": "Gestures, Location, Textual , Visual",
    "textual": "Title and Keyword",
    "visual": "Drawing, Icons, Static Visuals",
    "location": "3D Surface, Back 2D (Occlusion), Body, Physical Object",
    "gesture": "Animation Trigger, Follow-through, Highlight",
    "screenshots": "https://drive.google.com/drive/folders/1EO87jKNwDTU4NulQpvdntYeRjppNj5vO?usp=sharing"
  },
  {
    "video": "Adobe After Effects CS6 - 3D Text Motion Tracking",
    "link": "https://www.youtube.com/watch?v=-vuzkQHkQgk",
    "category": "Location, Textual ",
    "textual": "Title and Keyword",
    "visual": "",
    "location": "3D Surface, Front 2D",
    "gesture": "",
    "screenshots": "https://drive.google.com/drive/folders/1BTWS98WybOU9gBCeIW_AXREmFEwD9-Zz?usp=sharing"
  },
  {
    "video": "adobe photoshop fantastic voyage",
    "link": "https://www.youtube.com/watch?v=FfSnJdpFBb8",
    "category": "Gestures, Location, Textual , Visual",
    "textual": "Title and Keyword",
    "visual": "Drawing, Icons, Screens, Static Visuals",
    "location": "3D Surface, Body, Front 2D, Physical Object",
    "gesture": "",
    "screenshots": "https://drive.google.com/drive/folders/1JyXr6Rzzrit_6noptLaVKaZladqXUhjG?usp=sharing"
  },
  {
    "video": "All about Circles Chord, Diameter, and Radius for Class 4 & 5 Learn with BYJU'S",
    "link": "https://www.youtube.com/watch?v=CTDtiXHorgc",
    "category": "Gestures, Location, Textual , Visual",
    "textual": "Label and Annotation, List, Title and Keyword",
    "visual": "Graph, Static Visuals",
    "location": "Front 2D",
    "gesture": "Highlight, Move, Scale/Rotation, Specify Position",
    "screenshots": "https://drive.google.com/drive/folders/1r8TAFZjt8ptlLpBOsTGanGOJqO8if-WJ?usp=sharing"
  },
  {
    "video": "All About Lines Class 6 Learn With BYJU'S",
    "link": "https://www.youtube.com/watch?v=g5vXUjeImUw",
    "category": "Gestures, Location, Textual , Visual",
    "textual": "Label and Annotation, List, Title and Keyword",
    "visual": "Static Visuals, Videos",
    "location": "Back 2D (Occlusion), Front 2D",
    "gesture": "Animation Trigger, Highlight, Scale/Rotation, Specify Position",
    "screenshots": "https://drive.google.com/drive/folders/1wvsWnZ39lJRYhmgieY_RyDDHQmtmQngW?usp=sharing"
  },
  {
    "video": "Allstate Runner",
    "link": "https://vimeo.com/133075406",
    "category": "Gestures, Location, Textual , Visual",
    "textual": "Label and Annotation",
    "visual": "Static Visuals",
    "location": "3D Surface, Back 2D (Occlusion), Body, Front 2D, Physical Object",
    "gesture": "Follow-through, Highlight",
    "screenshots": "https://drive.google.com/drive/folders/1KhELQRMhFxVg2STWj5rS3_hVHEHPOKpI?usp=sharing"
  },
  {
    "video": "AR Music Player",
    "link": "https://www.youtube.com/watch?v=ZNfUlvPf0lQ",
    "category": "Gestures, Location, Textual , Visual",
    "textual": "Profile, Title and Keyword",
    "visual": "Icons, Static Visuals",
    "location": "Front 2D",
    "gesture": "Highlight, Move",
    "screenshots": "https://drive.google.com/drive/folders/1-ObUSzOUsr-Fpf4FZgDtxQsjwlwxfLYt?usp=sharing"
  },
  {
    "video": "Astrophysics with Neil DeGrasse Tyson | Dark Matter, Particle Physics, & Cosmic Science",
    "link": "https://www.youtube.com/watch?v=Yz2vq_69hwU",
    "category": "Gestures, Location, Textual , Visual",
    "textual": "Label and Annotation, Title and Keyword",
    "visual": "Graph, Static Visuals, Videos",
    "location": "3D Surface, Back 2D (Occlusion), Body, Front 2D",
    "gesture": "Animation Trigger, Move, Scale/Rotation",
    "screenshots": "https://drive.google.com/drive/folders/1D316WC0wyJWk1sKq4B_mRloWHRrqUg1w?usp=sharing"
  },
  {
    "video": "AT&T - Kenny Smith",
    "link": "https://vimeo.com/165917246",
    "category": "Gestures, Location, Textual , Visual",
    "textual": "Profile",
    "visual": "Drawing, Icons, Static Visuals",
    "location": "3D Surface, Back 2D (Occlusion)",
    "gesture": "Animation Trigger, Move",
    "screenshots": "https://drive.google.com/drive/folders/1ghuH4UTZsThLO7Aiw_qePMruyRpoPPPQ?usp=sharing"
  },
  {
    "video": "Charter More",
    "link": "https://drive.google.com/file/d/1mg3mdAqX5GGi4EORZ3LiKPwRx3HPix1E/view?usp=sharing",
    "category": "Location, Textual , Visual",
    "textual": "Label and Annotation, Profile",
    "visual": "Drawing, Icons, Screens",
    "location": "Back 2D (Occlusion), Body, Front 2D, Physical Object",
    "gesture": "",
    "screenshots": "https://drive.google.com/drive/folders/1ETGxKr1_2pkF5-O5q_5IXNomVd5BRoG0?usp=sharing"
  },
  {
    "video": "Circles Introduction",
    "link": "https://www.youtube.com/watch?v=m9dpeG2rKdY",
    "category": "Gestures, Location, Textual , Visual",
    "textual": "List, Title and Keyword",
    "visual": "Drawing, Graph, Static Visuals",
    "location": "Back 2D (Occlusion), Front 2D",
    "gesture": "Highlight, Scale/Rotation, Specify Position",
    "screenshots": "https://drive.google.com/drive/folders/1vykkqB8iv8dvOsm2VddOMpr4WBU8V8Gc?usp=sharing"
  },
  {
    "video": "Circles and their Chords | Learn with BYJU'S",
    "link": "https://www.youtube.com/watch?v=Jw-fijHnAjk",
    "category": "Gestures, Location, Textual , Visual",
    "textual": "Title and Keyword",
    "visual": "Drawing",
    "location": "Front 2D",
    "gesture": "Highlight, Move, Specify Position",
    "screenshots": "https://drive.google.com/drive/folders/12RL6_m-c-aK8VJUkPqqdzMlNCiEYwDj6?usp=sharing"
  },
  {
    "video": "Clearly Contacts Saving Money",
    "link": "https://vimeo.com/10904876",
    "category": "Gestures, Location, Textual , Visual",
    "textual": "Label and Annotation, List, Title and Keyword",
    "visual": "Icons",
    "location": "3D Surface, Physical Object",
    "gesture": "",
    "screenshots": "https://drive.google.com/drive/folders/1N6ak8r90LzXfF6Q8vDISiIPhiM1h9_l5?usp=sharing"
  },
  {
    "video": "Concave And Convex Mirrors Explanation Difference Between Concave and Convex Mirrors",
    "link": "https://www.youtube.com/watch?v=3-iE-6gTIZE",
    "category": "Gestures, Location, Textual , Visual",
    "textual": "Label and Annotation, Title and Keyword",
    "visual": "Drawing, Graph, Static Visuals",
    "location": "Front 2D",
    "gesture": "Highlight, Move, Specify Position",
    "screenshots": "https://drive.google.com/drive/folders/11rDpIug9zD1sTfB4Tug7oqNhK-642EuJ?usp=sharing"
  },
  {
    "video": "Cool Math Trick With Rectangle And Triangle #Shorts",
    "link": "https://www.youtube.com/shorts/UULqlIxQImI",
    "category": "Gestures, Location, Textual , Visual",
    "textual": "Title and Keyword",
    "visual": "Drawing, Static Visuals",
    "location": "Front 2D",
    "gesture": "Animation Trigger, Highlight, Move, Specify Position",
    "screenshots": "https://drive.google.com/drive/folders/1gb_AkKa4hOvDr72XeA5uMZ1hzkkGOYXh?usp=sharing"
  },
  {
    "video": "Corporate Video Schiavello",
    "link": "https://www.youtube.com/watch?v=nhorF9qNCUg",
    "category": "Location, Textual , Visual",
    "textual": "List, Speech Bubble, Title and Keyword",
    "visual": "Graph, Static Visuals",
    "location": "3D Surface, Back 2D (Occlusion)",
    "gesture": "",
    "screenshots": "https://drive.google.com/drive/folders/13OzFa70g1g4q3UJvXcU4Go__PbPTIvsB?usp=sharing"
  },
  {
    "video": "Create Callout Titles For Your Footage After Effects Tutorial",
    "link": "https://www.youtube.com/watch?v=ywnKh121gIo",
    "category": "Location, Textual , Visual",
    "textual": "Label and Annotation, Title and Keyword",
    "visual": "Static Visuals",
    "location": "Back 2D (Occlusion), Physical Object",
    "gesture": "",
    "screenshots": "https://drive.google.com/drive/folders/128bWLMWeGU_ghdkkPdLG88Ow6WcGH9HZ?usp=sharing"
  },
  {
    "video": "DAIV PV Kentaro Osawa",
    "link": "https://vimeo.com/331524688",
    "category": "Location, Textual , Visual",
    "textual": "Title and Keyword",
    "visual": "Static Visuals",
    "location": "3D Surface, Physical Object",
    "gesture": "",
    "screenshots": "https://drive.google.com/drive/folders/1OLx1958Nd1antd8PYBQbjGrjSckmSAa2?usp=sharing"
  },
  {
    "video": "Dassault Aviation Higher Together",
    "link": "https://www.youtube.com/watch?v=XgtZE43TcAk",
    "category": "Gestures, Location, Textual , Visual",
    "textual": "",
    "visual": "Graph, Screens, Static Visuals",
    "location": "3D Surface, Back 2D (Occlusion), Body, Front 2D",
    "gesture": "Highlight, Move, Scale/Rotation, Specify Position",
    "screenshots": "https://drive.google.com/drive/folders/19mMZOki5Wst6uNiCHzz1xTyjcqwYGPkj?usp=sharing"
  },
  {
    "video": "DAVE Season 1 I’m DAVE Teaser - Starring Lil Dicky FXX",
    "link": "https://www.youtube.com/watch?v=Qhak9a68IzM",
    "category": "Gestures, Location, Textual , Visual",
    "textual": "Label and Annotation, Title and Keyword",
    "visual": "Drawing, Icons, Static Visuals",
    "location": "3D Surface, Back 2D (Occlusion), Body, Front 2D, Physical Object",
    "gesture": "Animation Trigger, Specify Position",
    "screenshots": "https://drive.google.com/drive/folders/1_KMBxUhrfrli3FxhQCGwSqL1OsyYyRtD?usp=sharing"
  },
  {
    "video": "Dell - Precision 5750",
    "link": "https://drive.google.com/file/d/1Z-KHSoyskTA432RVqGPHzksgW8uuDmb6/view?usp=sharing",
    "category": "Gestures, Location, Textual , Visual",
    "textual": "Title and Keyword",
    "visual": "Screens, Static Visuals",
    "location": "3D Surface, Front 2D",
    "gesture": "Move, Scale/Rotation",
    "screenshots": "https://drive.google.com/drive/folders/1T_pseGnecDqXac2fr1F4zAexLe2BJy3b?usp=sharing"
  },
  {
    "video": "Discovery Adventure Season",
    "link": "https://drive.google.com/file/d/1WYOveeglLlV80x3xkpfymyWbvuetwO_Z/view?usp=sharing",
    "category": "Gestures, Location, Textual , Visual",
    "textual": "Label and Annotation, List, Speech Bubble, Title and Keyword",
    "visual": "Icons, Static Visuals",
    "location": "Body, Front 2D",
    "gesture": "Follow-through, Move, Scale/Rotation",
    "screenshots": "https://drive.google.com/drive/folders/1UZpojcn3qGvIMACpi_xFJggDDgayz47E?usp=sharing"
  },
  {
    "video": "Dotdotdot",
    "link": "https://drive.google.com/file/d/1idY57sAU1obZl--wKdDn8FLVkmov8EQd/view?usp=sharing",
    "category": "Gestures, Location, Visual",
    "textual": "",
    "visual": "Static Visuals",
    "location": "3D Surface, Front 2D",
    "gesture": "Animation Trigger, Highlight",
    "screenshots": "https://drive.google.com/file/d/1idY57sAU1obZl--wKdDn8FLVkmov8EQd/view?usp=sharing"
  },
  {
    "video": "Echo park intro",
    "link": "https://vimeo.com/163358283",
    "category": "Gestures, Location, Textual , Visual",
    "textual": "Label and Annotation, List, Profile, Title and Keyword",
    "visual": "Icons, Static Visuals",
    "location": "3D Surface, Back 2D (Occlusion), Body, Front 2D",
    "gesture": "Animation Trigger, Highlight, Move, Specify Position",
    "screenshots": "https://drive.google.com/drive/folders/1sf0xWyyKUX_4JCia8Ych8GojmzLxS3ju?usp=sharing"
  },
  {
    "video": "Facebook Food Fight",
    "link": "https://drive.google.com/file/d/1hcJdBImrc3MaEZJeu62g7cfj4Yyv8YPm/view?usp=sharing",
    "category": "",
    "textual": "Speech Bubble, Title and Keyword",
    "visual": "Screens, Static Visuals",
    "location": "3D Surface, Body, Front 2D, Physical Object",
    "gesture": "Specify Position",
    "screenshots": "https://drive.google.com/drive/folders/1yQHqQ35ZjM5CX6ISoGcj2KlWa1WwLRlr?usp=sharing"
  },
  {
    "video": "Facebook Love",
    "link": "https://drive.google.com/file/d/1F9saacU_ElmH5kfRp4zLcJ8cpZocL_cD/view?usp=sharing",
    "category": "Gestures, Location, Textual , Visual",
    "textual": "Speech Bubble",
    "visual": "Icons, Screens, Static Visuals",
    "location": "Body, Front 2D",
    "gesture": "Animation Trigger, Move, Specify Position",
    "screenshots": "https://drive.google.com/drive/folders/1FTbq2fzpLmdGoWMOF2tHZnWAtwiEwA7f"
  },
  {
    "video": "Entaag Qatar Opening Sequence",
    "link": "https://m.facebook.com/Madology00/videos/entaag-qatar-production-of-qatar-opening-sequence-opener-motiongraphics-openings/126202338159097/?__so__=permalink&__rv__=related_videos",
    "category": "Gestures, Location, Textual , Visual",
    "textual": "Title and Keyword",
    "visual": "Static Visuals",
    "location": "Body, Front 2D, Physical Object",
    "gesture": "Follow-through",
    "screenshots": "https://drive.google.com/drive/folders/1CfZTGdqYEzQpQoYUvZLuCVU6feuTalQJ?usp=sharing"
  },
  {
    "video": "Ericsson-Business Users Survey -Commercial",
    "link": "https://drive.google.com/file/d/1Bxtpc4Q4mKDtcFCWuI2Qn-MQN26YsxE2/view?usp=sharing",
    "category": "Gestures, Location, Textual , Visual",
    "textual": "Label and Annotation, List, Profile, Title and Keyword",
    "visual": "Graph, Icons, Static Visuals",
    "location": "3D Surface, Back 2D (Occlusion), Body, Front 2D, Physical Object",
    "gesture": "Follow-through, Highlight, Move, Specify Position",
    "screenshots": "https://drive.google.com/drive/folders/1CLGT_LDT9s740J0sodW_EhOTdgqB0ziN?usp=sharing"
  },
  {
    "video": "Euramax Company Profile Video",
    "link": "https://vimeo.com/123926831",
    "category": "Location, Textual , Visual",
    "textual": "Label and Annotation, Title and Keyword",
    "visual": "Icons, Static Visuals",
    "location": "3D Surface, Front 2D, Physical Object",
    "gesture": "",
    "screenshots": "https://drive.google.com/drive/folders/1wFH1hcFHQ5WnUfEcpNsqgd89ExsEhk_S?usp=sharing"
  },
  {
    "video": "Explainer Video TSD",
    "link": "https://www.youtube.com/watch?v=dM_fW_8ARg4",
    "category": "Gestures, Location, Textual , Visual",
    "textual": "Label and Annotation, Profile, Title and Keyword",
    "visual": "Icons, Screens, Static Visuals, Videos",
    "location": "Front 2D",
    "gesture": "Animation Trigger, Highlight, Move, Specify Position",
    "screenshots": "https://drive.google.com/drive/folders/1q72plOXpw-2U0IcEFfVJ0btADyu4_81B?usp=sharing"
  },
  {
    "video": "EZtrader corporate video",
    "link": "https://vimeo.com/137267304",
    "category": "Gestures, Location, Textual , Visual",
    "textual": "Label and Annotation, Title and Keyword",
    "visual": "Graph, Icons, Static Visuals",
    "location": "3D Surface, Body, Front 2D, Physical Object",
    "gesture": "Highlight",
    "screenshots": "https://drive.google.com/drive/folders/1sGp_GJgnbcYbQ0iaS_GN_uc90qb0ociu?usp=sharing"
  },
  {
    "video": "FeelCapital corporate video",
    "link": "https://vimeo.com/98023574",
    "category": "Location, Textual , Visual",
    "textual": "Label and Annotation, List, Title and Keyword",
    "visual": "Graph, Icons, Static Visuals",
    "location": "3D Surface, Back 2D (Occlusion), Front 2D, Physical Object",
    "gesture": "",
    "screenshots": "https://drive.google.com/drive/folders/1UHFsqLHWFbu49Yi2lhfgxsrftKhn9rlg?usp=sharing"
  },
  {
    "video": "Finding The Square Root Of A Number I Class 9 I Learn With BYJU'S",
    "link": "https://www.youtube.com/watch?v=ML8Ugc_ZVTs",
    "category": "Gestures",
    "textual": "List",
    "visual": "Graph",
    "location": "Front 2D",
    "gesture": "Highlight, Move, Specify Position",
    "screenshots": "https://drive.google.com/drive/folders/1c1A5r_2eg-jPxI9ZAgPL5F3kILMw32kT?usp=sharing"
  },
  {
    "video": "Finding the Volume Of Cubes And Cuboids Class 4 Learn With BYJU'S",
    "link": "https://www.youtube.com/watch?v=dAxt3ud9eKI",
    "category": "Gestures, Location, Textual , Visual",
    "textual": "Label and Annotation, Title and Keyword",
    "visual": "Screens, Static Visuals",
    "location": "3D Surface, Front 2D, Physical Object",
    "gesture": "Animation Trigger, Highlight, Specify Position",
    "screenshots": "https://drive.google.com/drive/folders/1Nyiv2t9ngVbxTpUV3tmMQy7ToOylRFw7?usp=sharing"
  },
  {
    "video": "Fintro Infographic",
    "link": "https://www.pinterest.com/pin/455708056042451078/",
    "category": "Gestures, Location, Textual , Visual",
    "textual": "Label and Annotation, List, Title and Keyword",
    "visual": "Icons, Static Visuals",
    "location": "Back 2D (Occlusion), Body, Front 2D",
    "gesture": "Animation Trigger, Follow-through, Move",
    "screenshots": "https://drive.google.com/drive/folders/1HlEPtgNcNOlmWx_wk9oOsjm7ORDkW5ky?usp=sharing"
  },
  {
    "video": "Fixodent Plus",
    "link": "https://www.youtube.com/watch?v=oYnq6JZ2SRg",
    "category": "Gestures, Location, Textual , Visual",
    "textual": "Title and Keyword",
    "visual": "Static Visuals",
    "location": "3D Surface, Front 2D",
    "gesture": "Move",
    "screenshots": "https://drive.google.com/drive/folders/1xSLzmtSycSmivbFEK044N9gKfckG-fcx?usp=sharing"
  },
  {
    "video": "Formation of Soil",
    "link": "https://www.youtube.com/watch?v=0aDaNGhusN8",
    "category": "Gestures, Location, Textual , Visual",
    "textual": "Label and Annotation, List, Title and Keyword",
    "visual": "Static Visuals",
    "location": "Front 2D",
    "gesture": "Highlight, Move, Specify Position",
    "screenshots": "https://drive.google.com/drive/folders/1sgqR3NcP2VpRhoeUuPsfIXycX1lxhVRH?usp=sharing"
  },
  {
    "video": "Freescale - Vision of the Future- Industrial",
    "link": "https://vimeo.com/24287425",
    "category": "Gestures, Location, Textual , Visual",
    "textual": "Label and Annotation, List, Title and Keyword",
    "visual": "Graph, Static Visuals, Videos",
    "location": "3D Surface, Front 2D, Physical Object",
    "gesture": "Follow-through, Move, Specify Position",
    "screenshots": "https://drive.google.com/drive/folders/1XoMDeRgulRmht1WPvTlKls6oX2jm75kg?usp=sharing"
  },
  {
    "video": "Fugo-Brand Animation",
    "link": "https://www.youtube.com/watch?v=J4QpSvP8SJ4",
    "category": "Location, Textual , Visual",
    "textual": "Label and Annotation, Speech Bubble, Title and Keyword",
    "visual": "Graph, Icons, Screens, Static Visuals, Videos",
    "location": "3D Surface, Back 2D (Occlusion), Front 2D, Physical Object",
    "gesture": "",
    "screenshots": "https://drive.google.com/drive/folders/1qAgC5bRUN4xJ6rroPW_g7T3G5BT_zOWj?usp=sharing"
  },
  {
    "video": "Future Friendly Kids - Cascade",
    "link": "https://vimeo.com/61256441",
    "category": "Location, Visual",
    "textual": "Speech Bubble",
    "visual": "Drawing",
    "location": "Back 2D (Occlusion), Body, Front 2D",
    "gesture": "",
    "screenshots": "https://drive.google.com/drive/folders/18d78qPWBafziLgcck4K3WzufZQa2c0DP?usp=sharing"
  },
  {
    "video": "Bien Tasty cozinha com paçoca #TASTYPELOMUNDO ",
    "link": "https://www.youtube.com/watch?v=tKmIYCknT88",
    "category": "Location, Textual ",
    "textual": "Profile, Title and Keyword",
    "visual": "",
    "location": "Front 2D",
    "gesture": "",
    "screenshots": ""
  },
  {
    "video": "Duckwrth Gives A Thrift Store Makeover",
    "link": "https://www.youtube.com/watch?v=79XV6mEvtp4",
    "category": "Location, Textual , Visual",
    "textual": "Profile, Title and Keyword",
    "visual": "Static Visuals",
    "location": "Front 2D",
    "gesture": "",
    "screenshots": ""
  },
  {
    "video": "My Crazy Prom Story ",
    "link": "https://www.youtube.com/watch?v=dtV5ZmG6WoE",
    "category": "Location, Textual , Visual",
    "textual": "Label and Annotation, Title and Keyword",
    "visual": "Static Visuals, Videos",
    "location": "Front 2D",
    "gesture": "",
    "screenshots": ""
  },
  {
    "video": "How To Make Tempura At Home • Tasty",
    "link": "https://www.youtube.com/watch?v=oEiNJdNLqSA",
    "category": "Location, Textual , Visual",
    "textual": "List, Profile, Title and Keyword",
    "visual": "Videos",
    "location": "Front 2D",
    "gesture": "",
    "screenshots": ""
  },
  {
    "video": "DIY Fox Pumpkins _ No-Carve Pumpkin Idea",
    "link": "https://www.youtube.com/watch?v=2kHZWkWsQc8",
    "category": "Location, Textual ",
    "textual": "Label and Annotation, Title and Keyword",
    "visual": "",
    "location": "Front 2D",
    "gesture": "",
    "screenshots": ""
  },
  {
    "video": "Is This Food Or Something Else - Chocolate or Rocks • Tasty",
    "link": "https://www.youtube.com/watch?v=Vt4nofS-K1g",
    "category": "Location, Textual , Visual",
    "textual": "Label and Annotation, List, Profile, Title and Keyword",
    "visual": "Videos",
    "location": "Front 2D",
    "gesture": "",
    "screenshots": ""
  },
  {
    "video": "Krept and Konan Play Sour Barz",
    "link": "https://www.youtube.com/watch?v=0rU8cB5G4Us",
    "category": "Location, Textual , Visual",
    "textual": "List, Title and Keyword",
    "visual": "Static Visuals",
    "location": "Front 2D",
    "gesture": "",
    "screenshots": ""
  },
  {
    "video": "Can This Chef Make Instant Ramen Fancy",
    "link": "https://www.youtube.com/watch?v=w7CtP73taJA",
    "category": "Location, Textual , Visual",
    "textual": "List, Profile, Title and Keyword",
    "visual": "Static Visuals, Videos",
    "location": "Front 2D",
    "gesture": "",
    "screenshots": ""
  },
  {
    "video": "Curly Tries Making Salvadorian Quesadillas",
    "link": "https://www.youtube.com/watch?v=Z16BBHdiggA",
    "category": "",
    "textual": "Profile, Title and Keyword",
    "visual": "Static Visuals, Videos",
    "location": "Front 2D",
    "gesture": "",
    "screenshots": ""
  },
  {
    "video": "Bill Nye Answers Science Questions From Twitter - Part 3 _ Tech Support _ WIRED",
    "link": "https://www.youtube.com/watch?v=FaCeZsOOKEY",
    "category": "Textual ",
    "textual": "Title and Keyword",
    "visual": "",
    "location": "",
    "gesture": "",
    "screenshots": ""
  },
  {
    "video": "A Guide to Photo Editing _ Part 3 - Mini Series _ Photoshop Express _ Three Discovery",
    "link": "https://drive.google.com/file/d/1G_kCVlrzreaTz_AO6mSM5lKvR1aRJiL_/view?usp=sharing",
    "category": "Textual , Visual",
    "textual": "Profile",
    "visual": "Icons, Screens",
    "location": "",
    "gesture": "",
    "screenshots": ""
  },
  {
    "video": "3 Top Huawei Tips _ Huawei Gestures _ Tools _ Three Discovery (2020) ",
    "link": "https://www.notion.so3 Top Huawei Tips _ Huawei Gestures _ Tools _ Three Discovery (2020) ",
    "category": "Location, Textual , Visual",
    "textual": "Title and Keyword",
    "visual": "Screens",
    "location": "3D Surface",
    "gesture": "",
    "screenshots": ""
  },
  {
    "video": "Automate your life _ IFTTT If This Then That app recommendation _ Discovery with Three ",
    "link": "https://www.youtube.com/watch?v=ibMOPGgIiiU",
    "category": "Textual , Visual",
    "textual": "Title and Keyword",
    "visual": "Icons, Screens, Static Visuals",
    "location": "",
    "gesture": "",
    "screenshots": ""
  },
  {
    "video": "Balancing A Chemical Equation I Class 10 I Learn With BYJU_S",
    "link": "https://www.youtube.com/watch?v=N7SbiJXUANo",
    "category": "Gestures, Location, Textual , Visual",
    "textual": "Title and Keyword",
    "visual": "Static Visuals",
    "location": "Back 2D (Occlusion), Front 2D",
    "gesture": "Animation Trigger, Highlight, Move, Specify Position",
    "screenshots": ""
  },
  {
    "video": "BlackLine Midsize Brand Video",
    "link": "https://www.youtube.com/watch?v=tKPQ2Da2sjs",
    "category": "Location, Textual , Visual",
    "textual": "Title and Keyword",
    "visual": "Graph, Icons",
    "location": "3D Surface, Back 2D (Occlusion)",
    "gesture": "",
    "screenshots": ""
  },
  {
    "video": "Can This Chef Make A Prawn-Hater Change His Mind • Tasty ",
    "link": "https://www.youtube.com/watch?v=m-Bx8whGHUg",
    "category": "Textual ",
    "textual": "List, Profile",
    "visual": "",
    "location": "",
    "gesture": "",
    "screenshots": ""
  },
  {
    "video": "Can This Chef Make Canned Tuna Fancy • Tasty",
    "link": "https://www.youtube.com/watch?v=3Fw9iIYBROM",
    "category": "Textual ",
    "textual": "List, Profile",
    "visual": "",
    "location": "",
    "gesture": "",
    "screenshots": ""
  },
  {
    "video": "Can This Pastry Chef Transform Peanut Butter _ Jelly Into A New Dessert • Tasty",
    "link": "https://www.youtube.com/watch?v=ikuZeUd2Uyg",
    "category": "Gestures, Textual , Visual",
    "textual": "Profile, Title and Keyword",
    "visual": "Icons, Videos",
    "location": "",
    "gesture": "Highlight",
    "screenshots": ""
  },
  {
    "video": "Can This Son Guess His Mom_s Cooking ",
    "link": "https://www.youtube.com/watch?v=GdvEkjMtHc8",
    "category": "Textual , Visual",
    "textual": "Title and Keyword",
    "visual": "Icons",
    "location": "",
    "gesture": "",
    "screenshots": ""
  },
  {
    "video": "Canada_needs_more_independent_journalism._Join_us.-vimeo-77548585-hls-akfire_interconnect_quic-1551",
    "link": "https://vimeo.com/77548585",
    "category": "Gestures, Location, Textual , Visual",
    "textual": "Title and Keyword",
    "visual": "Static Visuals, Videos",
    "location": "Front 2D",
    "gesture": "Highlight, Move, Specify Position",
    "screenshots": ""
  },
  {
    "video": "Chefs Review Favorite Late Night Meals [dZ04CrrhKgQ]",
    "link": "https://www.youtube.com/watch?v=dZ04CrrhKgQ",
    "category": "Textual ",
    "textual": "Profile, Title and Keyword",
    "visual": "",
    "location": "",
    "gesture": "",
    "screenshots": ""
  },
  {
    "video": "Connecting with Facebook _ Staying in touch with your loved ones _ Three Discovery (2020) [Z-eVnWjMukE]",
    "link": "https://www.youtube.com/watch?v=Z-eVnWjMukE",
    "category": "Textual , Visual",
    "textual": "List, Profile",
    "visual": "Icons, Screens",
    "location": "",
    "gesture": "",
    "screenshots": ""
  },
  {
    "video": "Dark Chocolate Cherry Date Bars by Marie Reginato [J9zX_1pnO0Y]",
    "link": "https://www.youtube.com/watch?v=J9zX_1pnO0Y",
    "category": "Textual , Visual",
    "textual": "Profile, Title and Keyword",
    "visual": "Videos",
    "location": "",
    "gesture": "",
    "screenshots": ""
  },
  {
    "video": "Dining On A $20,000 Flight",
    "link": "https://www.youtube.com/watch?v=NxjLSxf49J0",
    "category": "Location, Textual , Visual",
    "textual": "Label and Annotation, Title and Keyword",
    "visual": "Icons, Screens, Static Visuals",
    "location": "Front 2D, Physical Object",
    "gesture": "",
    "screenshots": ""
  },
  {
    "video": "Every Mind Matters _ Mental Health Awareness _ Discovery. With Three. (2019) [zGgenpFtaCg]",
    "link": "https://www.youtube.com/watch?v=zGgenpFtaCg",
    "category": "Textual , Visual",
    "textual": "Title and Keyword",
    "visual": "Screens, Static Visuals, Videos",
    "location": "",
    "gesture": "",
    "screenshots": ""
  },
  {
    "video": "Fast Food Spicy Chicken Sandwich Blind Taste Test [gCN_KDRoUqI]",
    "link": "https://www.youtube.com/watch?v=gCN_KDRoUqI",
    "category": "Location, Textual , Visual",
    "textual": "Label and Annotation, Profile",
    "visual": "Icons",
    "location": "Front 2D",
    "gesture": "",
    "screenshots": ""
  },
  {
    "video": "Geometry Introduction",
    "link": "https://www.youtube.com/watch?v=GqdJFFvsZeE",
    "category": "Gestures, Location, Textual , Visual",
    "textual": "Title and Keyword",
    "visual": "Drawing, Static Visuals",
    "location": "Front 2D",
    "gesture": "Highlight, Move, Scale/Rotation, Specify Position",
    "screenshots": ""
  },
  {
    "video": "Get started with YouTube _ Find content right for you _ Happy streaming! _ Three Discovery (2020) [t6DH0pmyMs0]",
    "link": "https://drive.google.com/file/d/10VWhRw0vFbDrou1m56xUPnl8FS1o1lWR/view?usp=sharing",
    "category": "Textual , Visual",
    "textual": "Profile, Title and Keyword",
    "visual": "Icons, Screens, Videos",
    "location": "",
    "gesture": "",
    "screenshots": ""
  },
  {
    "video": "Google Maps _ Explore More Maps _ Discovery. With Three (2018) [irWeC5vXKbY]",
    "link": "https://www.youtube.com/watch?v=irWeC5vXKbY",
    "category": "Textual , Visual",
    "textual": "Title and Keyword",
    "visual": "Icons, Videos",
    "location": "",
    "gesture": "",
    "screenshots": ""
  },
  {
    "video": "Gordon Ramsay Answers Cooking Questions From Twitter _ Tech Support _ WIRED",
    "link": "https://www.youtube.com/watch?v=kJ5PCbtiCpk",
    "category": "Textual , Visual",
    "textual": "Title and Keyword",
    "visual": "Static Visuals",
    "location": "",
    "gesture": "",
    "screenshots": ""
  },
  {
    "video": "Gravitation",
    "link": "https://www.youtube.com/watch?v=3H1Dq5I6Kn8",
    "category": "Location, Textual , Visual",
    "textual": "Title and Keyword",
    "visual": "Static Visuals",
    "location": "Back 2D (Occlusion), Front 2D",
    "gesture": "",
    "screenshots": ""
  },
  {
    "video": "Hey Google! _ Voice Assistant on your phone [How to] _ Discovery. With Three (2018) [Cse3G-iM7h0]",
    "link": "https://www.youtube.com/watch?v=Cse3G-iM7h0",
    "category": "Textual , Visual",
    "textual": "Title and Keyword",
    "visual": "Icons, Screens",
    "location": "",
    "gesture": "",
    "screenshots": ""
  },
  {
    "video": "Honor 9 only on Three _ First Look_ Favourite Features _ Three [84wW6fJBsKs]",
    "link": "https://www.youtube.com/watch?v=84wW6fJBsKs",
    "category": "Location, Textual ",
    "textual": "Title and Keyword",
    "visual": "",
    "location": "Front 2D",
    "gesture": "",
    "screenshots": ""
  },
  {
    "video": "Hot Sauce Challenge - Nursery Rhymes [h_jjFPB2luU]",
    "link": "https://www.youtube.com/watch?v=h_jjFPB2luU",
    "category": "Location, Textual ",
    "textual": "Profile, Title and Keyword",
    "visual": "",
    "location": "Front 2D",
    "gesture": "",
    "screenshots": ""
  },
  {
    "video": "How do we measure distances in space BYJU_S Fun Facts",
    "link": "https://www.youtube.com/watch?v=tL6ilD7GxME",
    "category": "Gestures, Location, Textual , Visual",
    "textual": "Title and Keyword",
    "visual": "Static Visuals, Videos",
    "location": "3D Surface, Front 2D, Physical Object",
    "gesture": "Follow-through",
    "screenshots": ""
  },
  {
    "video": "How Search Works",
    "link": "https://www.youtube.com/watch?v=IvdOYieNT9w",
    "category": "Location, Textual , Visual",
    "textual": "Label and Annotation, Profile",
    "visual": "Static Visuals",
    "location": "Back 2D (Occlusion), Front 2D",
    "gesture": "Specify Position",
    "screenshots": ""
  },
  {
    "video": "How to Edit Video _ Video Editing Apps _ Three Discovery (2020) [6D0n3uUUkZg]",
    "link": "https://www.youtube.com/watch?v=6D0n3uUUkZg",
    "category": "Visual",
    "textual": "Label and Annotation",
    "visual": "Icons, Screens, Static Visuals, Videos",
    "location": "",
    "gesture": "",
    "screenshots": ""
  },
  {
    "video": "How To Make A Holiday Vegetarian Wellington [VKdT0vD_DQE]",
    "link": "https://www.youtube.com/watch?v=VKdT0vD_DQE",
    "category": "Location, Textual , Visual",
    "textual": "Title and Keyword",
    "visual": "Static Visuals, Videos",
    "location": "Front 2D",
    "gesture": "",
    "screenshots": ""
  },
  {
    "video": "How To Make Rie_s Aquarium Cookies • Tasty [MuVFCVEPeFs]",
    "link": "https://www.youtube.com/watch?v=MuVFCVEPeFs",
    "category": "Location, Textual , Visual",
    "textual": "Profile, Title and Keyword",
    "visual": "Icons, Static Visuals, Videos",
    "location": "Front 2D",
    "gesture": "",
    "screenshots": ""
  },
  {
    "video": "How To Make Tempura At Home • Tasty [oEiNJdNLqSA]",
    "link": "https://www.youtube.com/watch?v=oEiNJdNLqSA",
    "category": "Textual , Visual",
    "textual": "List, Profile, Title and Keyword",
    "visual": "Videos",
    "location": "",
    "gesture": "",
    "screenshots": ""
  },
  {
    "video": "Huawei Mate 9 _ First Look_ Favourite Features _ Three [GvMkD4aHzHw]",
    "link": "https://www.youtube.com/watch?v=GvMkD4aHzHw",
    "category": "Location, Textual , Visual",
    "textual": "Title and Keyword",
    "visual": "Videos",
    "location": "Front 2D",
    "gesture": "",
    "screenshots": ""
  },
  {
    "video": "Huawei P10 and P10 Plus _ First look_ Favourite Features _ Three [jeIqK_s2Q9U]",
    "link": "https://www.youtube.com/watch?v=jeIqK_s2Q9U",
    "category": "Location, Textual , Visual",
    "textual": "List, Title and Keyword",
    "visual": "Videos",
    "location": "Front 2D",
    "gesture": "",
    "screenshots": ""
  },
  {
    "video": "I Try To Make Vegan Salmon With Carrots [Uu42LU3F9Gk]",
    "link": "https://www.youtube.com/watch?v=Uu42LU3F9Gk",
    "category": "Location, Textual , Visual",
    "textual": "Profile, Title and Keyword",
    "visual": "Icons, Static Visuals",
    "location": "Front 2D",
    "gesture": "",
    "screenshots": ""
  },
  {
    "video": "Imperial College London - Motion Graphics",
    "link": "https://vimeo.com/64313502",
    "category": "Gestures, Location, Textual , Visual",
    "textual": "Label and Annotation, Title and Keyword",
    "visual": "Graph, Icons, Static Visuals, Videos",
    "location": "Body, Front 2D, Physical Object",
    "gesture": "",
    "screenshots": ""
  },
  {
    "video": "Interactive Body-driven - youtube show - P1",
    "link": "https://dl.acm.org/doi/10.1145/3290605.3300852",
    "category": "Gestures, Location, Visual",
    "textual": "",
    "visual": "Icons, Static Visuals",
    "location": "Front 2D",
    "gesture": "Move, Scale/Rotation, Specify Position",
    "screenshots": ""
  },
  {
    "video": "Uniform Motion and Non Uniform Motion",
    "link": "https://byjus.com/physics/uniform-motion-and-non-uniform-motion/",
    "category": "Gestures, Location, Textual , Visual",
    "textual": "Title and Keyword",
    "visual": "Drawing, Static Visuals",
    "location": "Front 2D",
    "gesture": "Animation Trigger, Move",
    "screenshots": ""
  },
  {
    "video": "SNS Bank - Spoken Words",
    "link": "https://www.youtube.com/watch?v=5cTQ04Cp48o",
    "category": "Gestures, Location, Visual",
    "textual": "",
    "visual": "Static Visuals",
    "location": "3D Surface, Body, Physical Object",
    "gesture": "Animation Trigger, Follow-through",
    "screenshots": ""
  },
  {
    "video": "Refraction and Refractive Index Learn with BYJU_S",
    "link": "https://www.youtube.com/watch?v=4heHz65oVsI",
    "category": "Gestures, Location, Textual , Visual",
    "textual": "List, Title and Keyword",
    "visual": "Drawing, Static Visuals",
    "location": "Front 2D",
    "gesture": "Highlight, Move, Scale/Rotation, Specify Position",
    "screenshots": ""
  },
  {
    "video": "The Only Knife Skills Guide You Need",
    "link": "https://www.youtube.com/watch?v=aoqVGdmVlKk",
    "category": "Location, Textual ",
    "textual": "Title and Keyword",
    "visual": "",
    "location": "Front 2D",
    "gesture": "",
    "screenshots": ""
  },
  {
    "video": "The Wonderful Legacy Of India_s Architecture Class 6 Learn With BYJU_S",
    "link": "https://www.youtube.com/watch?v=3EV0dKIX3rM",
    "category": "Location, Textual , Visual",
    "textual": "List, Title and Keyword",
    "visual": "Static Visuals",
    "location": "Front 2D",
    "gesture": "",
    "screenshots": ""
  },
  {
    "video": "iOS 14 New iMessage Features _ Our Favourite iOS 14 Features _ Three Discovery (2020) [EFCa_HT0NgY]",
    "link": "https://www.youtube.com/watch?v=EFCa_HT0NgY",
    "category": "Visual",
    "textual": "",
    "visual": "Icons, Screens, Static Visuals, Videos",
    "location": "",
    "gesture": "",
    "screenshots": ""
  },
  {
    "video": "Irrational Numbers On The Number Line I Class 9 I Learn With BYJU_S",
    "link": "https://www.youtube.com/watch?v=aDKek9X4jC4",
    "category": "Gestures, Location, Textual , Visual",
    "textual": "Title and Keyword",
    "visual": "Drawing, Static Visuals",
    "location": "Front 2D",
    "gesture": "Animation Trigger, Highlight, Move, Scale/Rotation, Specify Position",
    "screenshots": ""
  },
  {
    "video": "Korean and Mexican People Swap Snacks ",
    "link": "https://www.youtube.com/watch?v=gMvDfAI6H4c",
    "category": "Textual ",
    "textual": "Profile, Title and Keyword",
    "visual": "",
    "location": "",
    "gesture": "",
    "screenshots": ""
  },
  {
    "video": "LG G6 _ First look_ Favourite features _ Three [Yar7dw55J4Q]",
    "link": "https://www.youtube.com/watch?v=Yar7dw55J4Q",
    "category": "Location, Textual , Visual",
    "textual": "Title and Keyword",
    "visual": "Videos",
    "location": "Front 2D",
    "gesture": "",
    "screenshots": ""
  },
  {
    "video": "Line Call Out Titles for Premiere Pro CC 2018 - 2020",
    "link": "https://www.motionelements.com/motion-graphics-template-14307255-line-call-out-titles-for-premiere-pro-cc-2018-2020",
    "category": "Textual ",
    "textual": "Label and Annotation",
    "visual": "",
    "location": "",
    "gesture": "",
    "screenshots": ""
  },
  {
    "video": "Lumosity - Emily",
    "link": "https://www.youtube.com/watch?v=WfIbIsVRDcM",
    "category": "Location, Visual",
    "textual": "",
    "visual": "Graph, Screens, Static Visuals",
    "location": "Back 2D (Occlusion), Body, Front 2D",
    "gesture": "",
    "screenshots": ""
  },
  {
    "video": "LuxTrust - 10 Years",
    "link": "https://www.youtube.com/watch?v=DW7bEoMYaJg",
    "category": "Location, Textual , Visual",
    "textual": "Label and Annotation",
    "visual": "Static Visuals",
    "location": "Front 2D",
    "gesture": "",
    "screenshots": ""
  },
  {
    "video": "Making millions fall in love with learning",
    "link": "https://www.youtube.com/watch?v=WRacT7kUNDc",
    "category": "Gestures, Location, Textual , Visual",
    "textual": "Label and Annotation, Profile, Title and Keyword",
    "visual": "Drawing, Graph, Static Visuals, Videos",
    "location": "3D Surface, Back 2D (Occlusion), Front 2D",
    "gesture": "Highlight, Move, Scale/Rotation, Specify Position",
    "screenshots": ""
  },
  {
    "video": "My Friends Roasted My Suitcase - Packing Therapy [g9rQZ0b2jxU]",
    "link": "https://www.youtube.com/watch?v=g9rQZ0b2jxU",
    "category": "Location, Textual ",
    "textual": "Label and Annotation, Profile",
    "visual": "",
    "location": "Front 2D",
    "gesture": "",
    "screenshots": ""
  },
  {
    "video": "Neodreams Infographic Korea",
    "link": "https://vimeo.com/371076063",
    "category": "Gestures, Location, Textual , Visual",
    "textual": "Label and Annotation, Title and Keyword",
    "visual": "Graph, Icons, Static Visuals",
    "location": "Front 2D",
    "gesture": "Move, Specify Position",
    "screenshots": ""
  },
  {
    "video": "NHS Health Education England - Dementia Awareness",
    "link": "https://vimeo.com/98028567",
    "category": "Location, Textual , Visual",
    "textual": "Profile, Title and Keyword",
    "visual": "Icons, Static Visuals",
    "location": "Back 2D (Occlusion), Front 2D",
    "gesture": "",
    "screenshots": ""
  },
  {
    "video": "No Recipe Challenge - Oreo Cookie Brownies • Tasty [AZbrxEtxJiY]",
    "link": "https://www.youtube.com/watch?v=oi-wpuRfmgI",
    "category": "Textual , Visual",
    "textual": "List, Profile, Title and Keyword",
    "visual": "Videos",
    "location": "",
    "gesture": "",
    "screenshots": ""
  },
  {
    "video": "Ohm_s Law and Resistance",
    "link": "https://www.youtube.com/watch?v=oi-wpuRfmgI",
    "category": "Location, Textual ",
    "textual": "Label and Annotation",
    "visual": "",
    "location": "Front 2D",
    "gesture": "",
    "screenshots": ""
  },
  {
    "video": "Parliamentary Form Of Governance Class 7 - Civics Learn With BYJU_S",
    "link": "https://www.youtube.com/watch?v=d9gsy_jdNT8",
    "category": "Location, Textual , Visual",
    "textual": "List",
    "visual": "Static Visuals",
    "location": "Front 2D",
    "gesture": "",
    "screenshots": ""
  },
  {
    "video": "PathFactory ChalkTalk- Content Activation",
    "link": "https://vimeo.com/371588177",
    "category": "Textual , Visual",
    "textual": "List, Profile",
    "visual": "Graph, Icons",
    "location": "",
    "gesture": "",
    "screenshots": ""
  },
  {
    "video": "Pedigree Infographic Shake-Off",
    "link": "https://vimeo.com/40259700",
    "category": "Gestures, Location, Textual , Visual",
    "textual": "Title and Keyword",
    "visual": "Static Visuals",
    "location": "3D Surface, Body",
    "gesture": "Animation Trigger",
    "screenshots": ""
  },
  {
    "video": "Projectile Motion - Basketball in Projectile Motion",
    "link": "https://www.youtube.com/watch?v=5GoQ2Vkkgn8",
    "category": "Gestures, Location, Textual , Visual",
    "textual": "Title and Keyword",
    "visual": "Drawing, Icons, Static Visuals, Videos",
    "location": "3D Surface, Front 2D",
    "gesture": "Move, Specify Position",
    "screenshots": ""
  },
  {
    "video": "Projectile Motion 02 - Falling Balls in Disguise",
    "link": "https://www.youtube.com/watch?v=uMrEEVRqUDE",
    "category": "Gestures, Location, Textual , Visual",
    "textual": "Title and Keyword",
    "visual": "Drawing, Graph, Videos",
    "location": "Front 2D",
    "gesture": "Animation Trigger",
    "screenshots": ""
  },
  {
    "video": "Projectile Motion 04 - Strange Range",
    "link": "https://www.youtube.com/watch?v=etsyTxK85-o",
    "category": "Gestures, Location, Textual , Visual",
    "textual": "Title and Keyword",
    "visual": "Graph",
    "location": "Front 2D",
    "gesture": "Animation Trigger, Highlight, Move, Specify Position",
    "screenshots": ""
  },
  {
    "video": "Pulp Fiction in Typography",
    "link": "https://www.youtube.com/watch?v=wF8f8w6HPoo",
    "category": "Location, Textual , Visual",
    "textual": "Title and Keyword",
    "visual": "Static Visuals",
    "location": "3D Surface, Back 2D (Occlusion), Body",
    "gesture": "",
    "screenshots": ""
  },
  {
    "video": "Razer Phone. Only on Three _ First Look_ Favourite Features _ Three (2017) [lJisv_1RObM]",
    "link": "https://www.youtube.com/watch?v=lJisv_1RObM",
    "category": "Location, Textual ",
    "textual": "Title and Keyword",
    "visual": "",
    "location": "Front 2D",
    "gesture": "",
    "screenshots": ""
  },
  {
    "video": "Social Media Privacy _ Who can see your posts _ Discovery with Three [NWL1-Yqyl2E]",
    "link": "https://www.youtube.com/watch?v=NWL1-Yqyl2E",
    "category": "Location, Textual , Visual",
    "textual": "Title and Keyword",
    "visual": "Icons, Videos",
    "location": "Front 2D",
    "gesture": "",
    "screenshots": ""
  },
  {
    "video": "Standard Deviation Formula",
    "link": "",
    "category": "Location, Textual , Visual",
    "textual": "Title and Keyword",
    "visual": "Graph",
    "location": "Front 2D",
    "gesture": "",
    "screenshots": ""
  },
  {
    "video": "Start a Blog _ Using WordPress _ Three Discovery (2020) [9ml-2M_gaPU]",
    "link": "https://www.youtube.com/watch?v=9ml-2M_gaPU",
    "category": "Location, Textual , Visual",
    "textual": "Profile",
    "visual": "Icons, Screens, Videos",
    "location": "Front 2D",
    "gesture": "",
    "screenshots": ""
  },
  {
    "video": "Symmetric and Skew symmetric matrix - Problem Solving Techniques",
    "link": "https://www.youtube.com/watch?v=v5abfTlztTc",
    "category": "Location, Textual , Visual",
    "textual": "Title and Keyword",
    "visual": "Static Visuals",
    "location": "Front 2D",
    "gesture": "",
    "screenshots": ""
  },
  {
    "video": "The factorisation of a Quadratic Polynomial Learn with BYJU_S",
    "link": "https://www.youtube.com/watch?v=2YthCDIeuig",
    "category": "Gestures, Location, Textual , Visual",
    "textual": "Title and Keyword",
    "visual": "Drawing, Icons, Static Visuals",
    "location": "Front 2D",
    "gesture": "Highlight, Move, Scale/Rotation, Specify Position",
    "screenshots": ""
  },
  {
    "video": "This is How Easy It Is to Lie With Statistics",
    "link": "https://www.youtube.com/watch?v=bVG2OQp6jEQ",
    "category": "Location, Textual , Visual",
    "textual": "Label and Annotation, Title and Keyword",
    "visual": "Graph, Icons, Static Visuals, Videos",
    "location": "Front 2D",
    "gesture": "",
    "screenshots": ""
  },
  {
    "video": "Types of Bond Ionic, Covalent, Coordinate, and Hydrogen Bonds",
    "link": "https://www.youtube.com/watch?v=DinMgWWwMUE",
    "category": "Gestures, Location, Textual , Visual",
    "textual": "Label and Annotation, Title and Keyword",
    "visual": "Static Visuals, Videos",
    "location": "3D Surface, Front 2D",
    "gesture": "Move, Specify Position",
    "screenshots": ""
  },
  {
    "video": "Types of Rocks and Rock Formation - Igneous, Sedimentary, and Metamorphic",
    "link": "https://www.youtube.com/watch?v=0FYeL3WMQJU",
    "category": "Gestures, Location, Textual ",
    "textual": "Title and Keyword",
    "visual": "Static Visuals, Videos",
    "location": "Back 2D (Occlusion)",
    "gesture": "",
    "screenshots": ""
  },
  {
    "video": "Walmart Hearts of Magic",
    "link": "https://www.youtube.com/watch?v=fMS5oJ6umio",
    "category": "Gestures, Location, Textual , Visual",
    "textual": "Title and Keyword",
    "visual": "Static Visuals",
    "location": "3D Surface, Back 2D (Occlusion), Body, Front 2D, Physical Object",
    "gesture": "Move, Scale/Rotation",
    "screenshots": ""
  },
  {
    "video": "What Are The Different Forms Of Government Around The World Class 9 Learn With BYJU_S",
    "link": "https://www.youtube.com/watch?v=uZRssHEyUfI",
    "category": "Location, Textual , Visual",
    "textual": "Title and Keyword",
    "visual": "Static Visuals, Videos",
    "location": "Back 2D (Occlusion), Front 2D",
    "gesture": "",
    "screenshots": ""
  },
  {
    "video": "What Is The March Equinox #KeepLearning",
    "link": "https://www.youtube.com/watch?v=3FJy6rrZl94",
    "category": "Gestures, Location, Textual , Visual",
    "textual": "Label and Annotation, Title and Keyword",
    "visual": "Drawing, Static Visuals",
    "location": "3D Surface, Back 2D (Occlusion), Front 2D",
    "gesture": "Animation Trigger, Highlight, Move, Scale/Rotation, Specify Position",
    "screenshots": ""
  },
  {
    "video": "What Makes An Ecosystem Class 7 - Geography Learn with BYJU_S",
    "link": "https://www.youtube.com/watch?v=kIVajKJ7nrE",
    "category": "Gestures, Location, Textual , Visual",
    "textual": "List, Title and Keyword",
    "visual": "Static Visuals, Videos",
    "location": "3D Surface, Back 2D (Occlusion), Front 2D",
    "gesture": "Highlight",
    "screenshots": ""
  },
  {
    "video": "Zoopla 30 sec",
    "link": "https://vimeo.com/74951596",
    "category": "",
    "textual": "Label and Annotation, Title and Keyword",
    "visual": "Icons, Static Visuals",
    "location": "3D Surface",
    "gesture": "Follow-through",
    "screenshots": ""
  },
  {
    "video": "Zendesk Support",
    "link": "https://www.youtube.com/watch?v=EZlaeKYNpf0",
    "category": "Gestures, Location, Textual , Visual",
    "textual": "Label and Annotation, Profile, Title and Keyword",
    "visual": "Graph, Icons, Screens, Static Visuals",
    "location": "3D Surface, Back 2D (Occlusion), Physical Object",
    "gesture": "Follow-through",
    "screenshots": ""
  },
  {
    "video": "You Asked For It Opener 2014",
    "link": "https://vimeo.com/105596617",
    "category": "Location, Textual , Visual",
    "textual": "List, Title and Keyword",
    "visual": "Static Visuals",
    "location": "Back 2D (Occlusion), Body, Front 2D",
    "gesture": "",
    "screenshots": ""
  },
  {
    "video": "Writers Room",
    "link": "https://vimeo.com/adamgault/writersroom",
    "category": "Location, Visual",
    "textual": "",
    "visual": "Static Visuals",
    "location": "Back 2D (Occlusion)",
    "gesture": "",
    "screenshots": ""
  },
  {
    "video": "World_s Most Viewed TikToks!",
    "link": "https://www.youtube.com/watch?v=v9WSjE3tIkg",
    "category": "Gestures, Location, Textual , Visual",
    "textual": "Title and Keyword",
    "visual": "Static Visuals, Videos",
    "location": "Front 2D",
    "gesture": "Animation Trigger",
    "screenshots": ""
  },
  {
    "video": "What Tulips and the Great Recession Have in Common_Bloomberg bonds explainer",
    "link": "https://vimeo.com/238613548",
    "category": "Location, Textual , Visual",
    "textual": "Profile, Speech Bubble, Title and Keyword",
    "visual": "Graph, Static Visuals, Videos",
    "location": "Back 2D (Occlusion), Front 2D",
    "gesture": "",
    "screenshots": ""
  },
  {
    "video": "Vision Critical Brand Teaser",
    "link": "https://vimeo.com/25040862",
    "category": "Gestures, Location, Textual , Visual",
    "textual": "Label and Annotation, List, Profile, Title and Keyword",
    "visual": "Graph, Icons, Screens, Static Visuals",
    "location": "3D Surface, Front 2D",
    "gesture": "Highlight, Move, Scale/Rotation, Specify Position",
    "screenshots": ""
  },
  {
    "video": "Verlo Mattress",
    "link": "https://vimeo.com/14406643",
    "category": "Gestures, Location, Textual , Visual",
    "textual": "Title and Keyword",
    "visual": "Static Visuals",
    "location": "Back 2D (Occlusion), Front 2D",
    "gesture": "Follow-through",
    "screenshots": ""
  },
  {
    "video": "tvN CoolKkaDang Program Package Design",
    "link": "https://vimeo.com/52993011",
    "category": "Location, Textual , Visual",
    "textual": "Profile, Title and Keyword",
    "visual": "Static Visuals",
    "location": "3D Surface, Back 2D (Occlusion), Body, Front 2D",
    "gesture": "",
    "screenshots": ""
  },
  {
    "video": "BBVA",
    "link": "https://vimeo.com/15657273",
    "category": "Gestures, Location, Textual , Visual",
    "textual": "Title and Keyword",
    "visual": "Graph, Icons, Screens, Static Visuals",
    "location": "3D Surface, Back 2D (Occlusion), Front 2D",
    "gesture": "Animation Trigger, Move",
    "screenshots": ""
  },
  {
    "video": "Bloomberg Businessweek Andrew McAfee interview-How a Startup Can Thrive in the Digital Age",
    "link": "https://vimeo.com/223630618",
    "category": "Gestures, Location, Textual , Visual",
    "textual": "List, Profile, Title and Keyword",
    "visual": "Screens, Static Visuals, Videos",
    "location": "Back 2D (Occlusion), Front 2D",
    "gesture": "Specify Position",
    "screenshots": ""
  },
  {
    "video": "GET - KANALVALG",
    "link": "https://vimeo.com/55101524",
    "category": "Gestures, Location, Textual , Visual",
    "textual": "Title and Keyword",
    "visual": "Icons, Static Visuals",
    "location": "3D Surface",
    "gesture": "Animation Trigger, Highlight, Move, Specify Position",
    "screenshots": ""
  },
  {
    "video": "Greater Reading Economic Partnership - Bill Khakis",
    "link": "https://vimeo.com/84734032",
    "category": "Location, Textual , Visual",
    "textual": "Profile, Title and Keyword",
    "visual": "Static Visuals",
    "location": "Back 2D (Occlusion), Front 2D",
    "gesture": "",
    "screenshots": ""
  },
  {
    "video": "GREP-TAB Industries",
    "link": "https://vimeo.com/65787306",
    "category": "Location, Textual , Visual",
    "textual": "Profile, Title and Keyword",
    "visual": "Graph, Static Visuals",
    "location": "Back 2D (Occlusion)",
    "gesture": "",
    "screenshots": ""
  },
  {
    "video": "How to Easily Motion Track Text in After Effects - Wistia",
    "link": "https://www.google.com/search?q=How+to+Easily+Motion+Track+Text+in+After+Effects+-+Wistia&rlz=1C1ONGR_enIN990IN990&sxsrf=APq-WBsAycJGm6-F0MCHRXTIzrPQxVbgsg:1649795950925&tbm=isch&source=iu&ictx=1&vet=1&fir=9hxAE9FbYIEG1M%252C2pWAk3Nsn023JM%252C_&usg=AI4_-kRglvk_O46ShzMLcnYSY0PyPCbggQ&sa=X&ved=2ahUKEwiT_OzssI_3AhUGfN4KHQWdC6cQ9QF6BAgMEAE#imgrc=9hxAE9FbYIEG1M",
    "category": "Gestures, Location, Textual , Visual",
    "textual": "Label and Annotation, Speech Bubble, Title and Keyword",
    "visual": "Screens, Static Visuals",
    "location": "Body, Front 2D",
    "gesture": "Animation Trigger, Move, Scale/Rotation",
    "screenshots": ""
  },
  {
    "video": "How to Study Physics Effectively _ Study With Me Physics Edition",
    "link": "https://www.youtube.com/watch?v=bZLKG43Qcps",
    "category": "Location, Textual ",
    "textual": "List, Title and Keyword",
    "visual": "",
    "location": "Front 2D",
    "gesture": "",
    "screenshots": ""
  },
  {
    "video": "ING Direct Credit Immobilier David Dalidec",
    "link": "https://vimeo.com/170446327",
    "category": "Gestures, Location, Textual , Visual",
    "textual": "Label and Annotation, Title and Keyword",
    "visual": "Graph, Static Visuals",
    "location": "Back 2D (Occlusion)",
    "gesture": "Animation Trigger, Move",
    "screenshots": ""
  },
  {
    "video": "Interactive Body-driven - meditate for 1 minute - P3",
    "link": "https://dl.acm.org/doi/pdf/10.1145/3290605.3300852",
    "category": "Gestures, Location, Textual , Visual",
    "textual": "Title and Keyword",
    "visual": "Drawing",
    "location": "Front 2D",
    "gesture": "Animation Trigger, Follow-through, Move, Scale/Rotation, Specify Position",
    "screenshots": ""
  },
  {
    "video": "Introducing AMO Blockchain",
    "link": "https://vimeo.com/267229859",
    "category": "Location, Textual , Visual",
    "textual": "List, Profile, Title and Keyword",
    "visual": "Static Visuals",
    "location": "Front 2D",
    "gesture": "",
    "screenshots": ""
  },
  {
    "video": "Inventing the Future of Connectivity",
    "link": "https://www.youtube.com/watch?v=pxX6r-xDgG4",
    "category": "Gestures, Location, Textual , Visual",
    "textual": "Profile",
    "visual": "Icons, Static Visuals",
    "location": "Back 2D (Occlusion), Front 2D",
    "gesture": "Animation Trigger",
    "screenshots": ""
  },
  {
    "video": "MarketInvoice-Brand Video",
    "link": "https://www.youtube.com/watch?v=F-6c_wDvgsc",
    "category": "Gestures, Location, Textual , Visual",
    "textual": "Profile, Title and Keyword",
    "visual": "Screens",
    "location": "3D Surface, Back 2D (Occlusion)",
    "gesture": "Follow-through",
    "screenshots": ""
  },
  {
    "video": "Mattereum Blockchain Explainer Video",
    "link": "https://vimeo.com/262963300",
    "category": "Gestures, Location, Textual , Visual",
    "textual": "Profile, Speech Bubble, Title and Keyword",
    "visual": "Icons, Screens, Static Visuals",
    "location": "Front 2D",
    "gesture": "Specify Position",
    "screenshots": ""
  },
  {
    "video": "Morgan Crossing - Imagine",
    "link": "https://www.youtube.com/watch?v=Plrtpi_GfPk",
    "category": "Gestures, Location, Textual , Visual",
    "textual": "Label and Annotation, List, Profile, Title and Keyword",
    "visual": "Icons, Static Visuals",
    "location": "3D Surface, Body, Front 2D",
    "gesture": "Animation Trigger, Follow-through, Highlight, Move, Scale/Rotation, Specify Position",
    "screenshots": ""
  },
  {
    "video": "Networked Society Introduction",
    "link": "https://vimeo.com/31723662",
    "category": "Gestures, Location, Textual , Visual",
    "textual": "Label and Annotation, Profile, Title and Keyword",
    "visual": "Icons, Static Visuals",
    "location": "3D Surface, Physical Object",
    "gesture": "Follow-through, Move, Specify Position",
    "screenshots": ""
  },
  {
    "video": "Obama on what most Americans get wrong about foreign aid",
    "link": "https://www.youtube.com/watch?v=nzL_avUIlEE",
    "category": "Gestures, Location, Textual , Visual",
    "textual": "Title and Keyword",
    "visual": "Graph, Static Visuals, Videos",
    "location": "3D Surface, Front 2D",
    "gesture": "Move, Specify Position",
    "screenshots": ""
  },
  {
    "video": "PayPal Fast Simple and Secure",
    "link": "https://vimeo.com/93420558",
    "category": "Gestures, Location, Textual , Visual",
    "textual": "Title and Keyword",
    "visual": "Static Visuals, Videos",
    "location": "3D Surface, Back 2D (Occlusion), Front 2D",
    "gesture": "Animation Trigger, Highlight",
    "screenshots": ""
  },
  {
    "video": "Pilot FriXion Colors 30 second video",
    "link": "https://www.youtube.com/watch?v=4TZpxU0rMbg",
    "category": "Gestures, Location, Textual , Visual",
    "textual": "Title and Keyword",
    "visual": "Static Visuals",
    "location": "Back 2D (Occlusion), Body, Front 2D",
    "gesture": "Animation Trigger",
    "screenshots": ""
  },
  {
    "video": "Product Explainer Video Snips",
    "link": "https://vimeo.com/244996265",
    "category": "Location, Textual , Visual",
    "textual": "Label and Annotation, Speech Bubble",
    "visual": "Icons, Screens, Static Visuals, Videos",
    "location": "Front 2D",
    "gesture": "",
    "screenshots": ""
  },
  {
    "video": "Q-CTRL Educational Animation Series Ep 5-NISQ Era and Beyond",
    "link": "https://vimeo.com/423064309",
    "category": "Location, Textual , Visual",
    "textual": "List, Profile, Title and Keyword",
    "visual": "Screens, Static Visuals, Videos",
    "location": "3D Surface, Front 2D",
    "gesture": "",
    "screenshots": ""
  },
  {
    "video": "Rapido Prototyping Interactive AR Experiences through Programming by Demonstration",
    "link": "https://www.youtube.com/watch?v=nnMeLnikL6Y",
    "category": "Gestures, Location, Textual , Visual",
    "textual": "List, Title and Keyword",
    "visual": "Drawing, Icons, Static Visuals, Videos",
    "location": "3D Surface",
    "gesture": "Move, Specify Position",
    "screenshots": ""
  },
  {
    "video": "Savannah Morning News Light",
    "link": "https://vimeo.com/15159406",
    "category": "Gestures, Location, Textual , Visual",
    "textual": "Label and Annotation, Title and Keyword",
    "visual": "Graph, Static Visuals",
    "location": "3D Surface, Back 2D (Occlusion), Front 2D",
    "gesture": "Follow-through, Specify Position",
    "screenshots": ""
  },
  {
    "video": "SIDIZ TVCM-Manifesto",
    "link": "https://vimeo.com/149606145",
    "category": "Gestures, Location, Textual , Visual",
    "textual": "Label and Annotation, Title and Keyword",
    "visual": "Graph, Icons, Static Visuals",
    "location": "3D Surface, Back 2D (Occlusion), Front 2D, Physical Object",
    "gesture": "Animation Trigger",
    "screenshots": ""
  },
  {
    "video": "SJHH Did You Know",
    "link": "https://www.youtube.com/watch?v=lUIsx0LdO5k",
    "category": "Location, Textual , Visual",
    "textual": "Title and Keyword",
    "visual": "Icons, Static Visuals",
    "location": "Back 2D (Occlusion), Front 2D",
    "gesture": "",
    "screenshots": ""
  },
  {
    "video": "Surviving the Tornado IMR",
    "link": "https://www.youtube.com/watch?v=lUIsx0LdO5k",
    "category": "Gestures, Location, Textual , Visual",
    "textual": "Label and Annotation, List, Title and Keyword",
    "visual": "Static Visuals, Videos",
    "location": "3D Surface, Back 2D (Occlusion), Front 2D",
    "gesture": "Animation Trigger",
    "screenshots": ""
  },
  {
    "video": "Target Dare Dream Do Stoute and Morial",
    "link": "https://vimeo.com/22680496",
    "category": "Gestures, Location, Textual , Visual",
    "textual": "Title and Keyword",
    "visual": "Icons, Static Visuals",
    "location": "3D Surface, Back 2D (Occlusion), Body, Front 2D",
    "gesture": "Follow-through",
    "screenshots": ""
  },
  {
    "video": "The Visual Agency - Annual Report 2014",
    "link": "https://vimeo.com/123407907",
    "category": "Gestures, Location, Textual , Visual",
    "textual": "Profile, Title and Keyword",
    "visual": "Graph, Static Visuals, Videos",
    "location": "3D Surface, Body, Front 2D",
    "gesture": "Highlight, Move, Specify Position",
    "screenshots": ""
  },
  {
    "video": "HUD Test 3D Holographic Interface",
    "link": "https://vimeo.com/32664640",
    "category": "Gestures, Location, Textual , Visual",
    "textual": "Title and Keyword",
    "visual": "Static Visuals",
    "location": "3D Surface, Front 2D",
    "gesture": "Move, Scale/Rotation, Specify Position",
    "screenshots": ""
  },
  {
    "video": "HYUNDAI Jobworld",
    "link": "https://vimeo.com/124791434",
    "category": "Gestures, Location, Textual , Visual",
    "textual": "Label and Annotation, List, Title and Keyword",
    "visual": "Graph, Icons, Static Visuals",
    "location": "3D Surface, Back 2D (Occlusion), Front 2D",
    "gesture": "Specify Position",
    "screenshots": ""
  },
  {
    "video": "Interactive Body-driven - astronomy research paper presentation - P6",
    "link": "https://dl.acm.org/doi/pdf/10.1145/3290605.3300852",
    "category": "Gestures, Location, Textual , Visual",
    "textual": "Title and Keyword",
    "visual": "Drawing, Graph, Static Visuals",
    "location": "Back 2D (Occlusion), Front 2D",
    "gesture": "Animation Trigger, Move, Scale/Rotation, Specify Position",
    "screenshots": ""
  },
  {
    "video": "JFE Steel IRON CUBE",
    "link": "https://www.youtube.com/watch?v=yFQZkrIZm28",
    "category": "Location, Textual , Visual",
    "textual": "Label and Annotation, List, Title and Keyword",
    "visual": "Static Visuals",
    "location": "3D Surface, Front 2D, Physical Object",
    "gesture": "",
    "screenshots": ""
  },
  {
    "video": "RSM_Unique_Adnan-vimeo-218522123-dash-akfire_interconnect_quic-video-bbe1964a",
    "link": "https://vimeo.com/218522123",
    "category": "Location, Textual , Visual",
    "textual": "Profile, Title and Keyword",
    "visual": "Icons, Static Visuals",
    "location": "Back 2D (Occlusion), Front 2D",
    "gesture": "",
    "screenshots": ""
  },
  {
    "video": "The Mysterious Orbit of Mercury I The Great Courses",
    "link": "https://www.youtube.com/watch?v=hSXNE0pNtr8",
    "category": "Gestures, Location, Textual , Visual",
    "textual": "Label and Annotation, Title and Keyword",
    "visual": "Static Visuals",
    "location": "3D Surface, Back 2D (Occlusion), Front 2D",
    "gesture": "Animation Trigger, Specify Position",
    "screenshots": ""
  },
  {
    "video": "Zazzle The Future",
    "link": "https://vimeo.com/35984982",
    "category": "Gestures, Location, Textual , Visual",
    "textual": "List, Title and Keyword",
    "visual": "Static Visuals",
    "location": "3D Surface, Front 2D",
    "gesture": "Animation Trigger, Highlight, Move, Scale/Rotation, Specify Position",
    "screenshots": ""
  }
]